[[
  "1",
  "2",
  "3",
  "4"
],{
  "id": "5",
  "name": "6",
  "country": "7",
  "description": "8",
  "orders": "9",
  "specialties": "10",
  "comments": "11",
  "rating": 0,
  "jobs": "12"
},{
  "id": "13",
  "name": "14",
  "country": "15",
  "description": "16",
  "orders": "17",
  "specialties": "18",
  "comments": "19",
  "rating": 0,
  "jobs": "20"
},{
  "id": "21",
  "name": "22",
  "country": "23",
  "description": "23",
  "orders": "24",
  "specialties": "25",
  "comments": "26",
  "rating": 0,
  "jobs": "27"
},{
  "id": "28",
  "name": "29",
  "country": "23",
  "description": "23",
  "orders": "30",
  "specialties": "31",
  "comments": "32",
  "rating": 0,
  "jobs": "33"
},"70cdca3e-ee82-4a60-a6d5-43001b0ff1db","Freelancer1","turkeyy","too muych experienced",[],[
  "34"
],[],[
  "35"
],"d6b81ede-64a5-4194-a82e-d684358c7d04","Freelancer2","Turkey","I created Facebook",[
  "36",
  "37",
  "38"
],[
  "39",
  "40",
  "41"
],[],[
  "42",
  "43",
  "44"
],"d73a78a0-dc45-45a5-9c57-730fdb2bbe38","Freelancer3","",[
  "45",
  "46"
],[],[],[
  "47"
],"9b4cea19-7771-494e-a4d4-b25d07913e86","Tayfun",[],[],[],[],{
  "field": "48",
  "experience": "49"
},{
  "id": "50",
  "freelancer": "51",
  "title": "52",
  "content": "53",
  "price": "54",
  "deliveryTime": "55",
  "ratingsAndComments": "56",
  "employers": "57"
},{
  "id": "58",
  "employer": "59",
  "job": "42",
  "price": 30,
  "status": "60",
  "date": "61"
},{
  "id": "62",
  "employer": "59",
  "job": "43",
  "price": 50,
  "status": "63",
  "date": "61"
},{
  "id": "64",
  "employer": "65",
  "job": "66",
  "price": "67",
  "status": "68",
  "date": "69"
},{
  "field": "70",
  "experience": 10
},{
  "field": "71",
  "experience": 3
},{
  "field": "48",
  "experience": "49"
},{
  "id": "72",
  "freelancer": "73",
  "title": "74",
  "content": "75",
  "price": 30,
  "deliveryTime": 3,
  "ratingsAndComments": "76",
  "employers": "77"
},{
  "id": "78",
  "freelancer": "73",
  "title": "79",
  "content": "80",
  "price": 50,
  "deliveryTime": 7,
  "ratingsAndComments": "81",
  "employers": "82"
},{
  "id": "83",
  "freelancer": "84",
  "title": "85",
  "content": "86",
  "price": "67",
  "deliveryTime": "87",
  "ratingsAndComments": "88",
  "employers": "89"
},{
  "id": "90",
  "employer": "91",
  "job": "92",
  "price": "93",
  "status": "68",
  "date": "94"
},{
  "id": "95",
  "employer": "96",
  "job": "97",
  "price": "93",
  "status": "68",
  "date": "98"
},{
  "id": "99",
  "freelancer": "100",
  "title": "101",
  "content": "102",
  "price": "93",
  "deliveryTime": "103",
  "ratingsAndComments": "104",
  "employers": "105"
},"3d design","1 month","18b4bf23-4aa6-4909-931a-a64389babd53",{
  "id": "5",
  "name": "6",
  "country": "7",
  "description": "8",
  "orders": "9",
  "specialties": "10",
  "comments": "11",
  "rating": 0,
  "jobs": "12"
},"f1","f1böyledir","2f1l/h","32hf1ta",[],[],"aad9d2f4-b080-450b-a49b-b01165f2015f",{
  "id": "106",
  "name": "107",
  "orders": "108"
},"done","2021-01-12T03:58:00.218Z","870161f0-322a-4d62-9caf-5c6e05bb563c","inprogress","13365a27-1329-40b8-b313-2a95154f74db",{
  "id": "106",
  "name": "107",
  "orders": "109"
},{
  "id": "83",
  "freelancer": "84",
  "title": "85",
  "content": "86",
  "price": "67",
  "deliveryTime": "87",
  "ratingsAndComments": "88",
  "employers": "89"
},"220 tl/h","todo","2021-01-12T04:29:06.732Z","Web Development","Web Security","527f81ea-bed3-455d-af01-83d720ed9796",{
  "id": "13",
  "name": "14",
  "country": "15",
  "description": "16",
  "orders": "17",
  "specialties": "18",
  "comments": "19",
  "rating": 0,
  "jobs": "20"
},"Photoshop","Photoshop Master",[
  "110"
],[
  "59"
],"5d3dca2d-a6f6-412f-9fea-876342f294a5","Wordpress","All kind of websites",[
  "111"
],[
  "59"
],"8feb3e52-9762-4204-9db2-fc7fdfcb3a75",{
  "id": "13",
  "name": "14",
  "country": "15",
  "description": "16",
  "orders": "17",
  "specialties": "18",
  "comments": "19",
  "rating": 0,
  "jobs": "20"
},"f2nin işi","asdsd de böyledir","32hafta",[],[
  "65"
],"ca01e0b1-e363-4419-af70-f5c261121602",{
  "id": "112",
  "name": "113",
  "orders": "114"
},{
  "id": "99",
  "freelancer": "100",
  "title": "101",
  "content": "102",
  "price": "93",
  "deliveryTime": "103",
  "ratingsAndComments": "104",
  "employers": "105"
},"220 f3","2021-01-12T04:28:09.005Z","092bd9aa-c239-4f66-8c7a-f9c39863a24f",{
  "id": "112",
  "name": "113",
  "orders": "115"
},{
  "id": "99",
  "freelancer": "100",
  "title": "101",
  "content": "102",
  "price": "93",
  "deliveryTime": "103",
  "ratingsAndComments": "104",
  "employers": "105"
},"2021-01-12T04:28:19.751Z","ce63cbfc-4247-40e6-8ea2-09f2d722b81e",{
  "id": "21",
  "name": "22",
  "country": "23",
  "description": "23",
  "orders": "24",
  "specialties": "25",
  "comments": "26",
  "rating": 0,
  "jobs": "27"
},"f3 işi","f3 böyledir","f3 hafta",[],[
  "91",
  "96"
],"ee9a2362-9297-4065-8dbd-98b4cae2c265","Employer1",[
  "36",
  "37"
],[
  "116",
  "117",
  "38"
],{
  "rating": 4,
  "comment": "118"
},{
  "rating": 2,
  "comment": "119"
},"ae363ff3-e9ca-4b05-b2d1-c6039ba8e0ca","Employer4",[
  "45"
],[
  "120",
  "46"
],{
  "id": "58",
  "employer": "121",
  "job": "122",
  "price": 30,
  "status": "60",
  "date": "61"
},{
  "id": "62",
  "employer": "121",
  "job": "123",
  "price": 50,
  "status": "63",
  "date": "61"
},"Great job!","Shitty job!",{
  "id": "90",
  "employer": "124",
  "job": "125",
  "price": "93",
  "status": "68",
  "date": "94"
},{
  "id": "106",
  "name": "107",
  "orders": "109"
},{
  "id": "72",
  "freelancer": "126",
  "title": "74",
  "content": "75",
  "price": 30,
  "deliveryTime": 3,
  "ratingsAndComments": "127",
  "employers": "128"
},{
  "id": "78",
  "freelancer": "126",
  "title": "79",
  "content": "80",
  "price": 50,
  "deliveryTime": 7,
  "ratingsAndComments": "129",
  "employers": "130"
},{
  "id": "112",
  "name": "113",
  "orders": "115"
},{
  "id": "99",
  "freelancer": "131",
  "title": "101",
  "content": "102",
  "price": "93",
  "deliveryTime": "103",
  "ratingsAndComments": "132",
  "employers": "133"
},{
  "id": "13",
  "name": "14",
  "country": "15",
  "description": "16",
  "orders": "134",
  "specialties": "135",
  "comments": "136",
  "rating": 0,
  "jobs": "137"
},[
  "138"
],[
  "121"
],[
  "139"
],[
  "121"
],{
  "id": "21",
  "name": "22",
  "country": "23",
  "description": "23",
  "orders": "140",
  "specialties": "141",
  "comments": "142",
  "rating": 0,
  "jobs": "143"
},[],[
  "124"
],[
  "116",
  "117"
],[
  "144",
  "145"
],[],[
  "122",
  "123"
],{
  "rating": 4,
  "comment": "118"
},{
  "rating": 2,
  "comment": "119"
},[
  "120"
],[],[],[
  "146"
],{
  "field": "70",
  "experience": 10
},{
  "field": "71",
  "experience": 3
},{
  "id": "99",
  "freelancer": "131",
  "title": "101",
  "content": "102",
  "price": "93",
  "deliveryTime": "103",
  "ratingsAndComments": "132",
  "employers": "133"
}]